Grortir-0.1.8.dist-info/DESCRIPTION.rst
Grortir-0.1.8.dist-info/METADATA
Grortir-0.1.8.dist-info/RECORD
Grortir-0.1.8.dist-info/WHEEL
Grortir-0.1.8.dist-info/entry_points.txt
Grortir-0.1.8.dist-info/metadata.json
Grortir-0.1.8.dist-info/top_level.txt
grortir/__init__.py
grortir/sample.py
grortir/externals/__init__.py
grortir/externals/pyswarm/__init__.py
grortir/externals/pyswarm/pso.py
grortir/main/__init__.py
grortir/main/controller/__init__.py
grortir/main/model/__init__.py
grortir/main/model/core/__init__.py
grortir/main/model/core/abstract_process.py
grortir/main/model/core/abstract_stage.py
grortir/main/model/core/optimization_status.py
grortir/main/model/processes/__init__.py
grortir/main/model/processes/calls_process.py
grortir/main/model/processes/factories/__init__.py
grortir/main/model/processes/factories/calls_process_factory.py
grortir/main/model/stages/__init__.py
grortir/main/model/stages/calls_stage.py
grortir/main/optimizers/__init__.py
grortir/main/optimizers/base_optimizer.py
grortir/main/optimizers/grouped_optimizer.py
grortir/main/optimizers/grouping_strategy.py
grortir/main/optimizers/optimizer.py
grortir/main/optimizers/result.py
grortir/main/pso/__init__.py
grortir/main/pso/calls_group_optimization_strategy.py
grortir/main/pso/calls_optimization_strategy.py
grortir/main/pso/group_optimization_strategy.py
grortir/main/pso/optimization_controller.py
grortir/main/pso/optimization_strategy.py
grortir/main/pso/particle.py
grortir/main/pso/position_updater.py
grortir/main/pso/process_validator.py
grortir/main/pso/pso_algorithm.py
grortir/main/pso/swarm.py
grortir/main/pso/velocity_calculator.py
grortir/main/pso/whole_group_pso.py
grortir/main/view/__init__.py
grortir/scripts/Optimization.py
grortir/scripts/__init__.py
grortir/test/__init__.py
grortir/test/conftest.py
grortir/test/test_grortir.py
grortir/test/controller/__init__.py
grortir/test/externals/__init__.py
grortir/test/externals/pyswarm/__init__.py
grortir/test/externals/pyswarm/test_pyswarm.py
grortir/test/model/__init__.py
grortir/test/model/core/__init__.py
grortir/test/model/core/test_abstract_process.py
grortir/test/model/core/test_abstract_stage.py
