Metadata-Version: 2.0
Name: Grortir
Version: 0.1.8
Summary: Application for supporting
Home-page: https://github.com/qbahn/grortir
Author: Wojtek Pietrucha
Author-email: wojtekpietrucha@gmail.com
License: MIT
Platform: UNKNOWN
Classifier: Development Status :: 1 - Planning
Classifier: Natural Language :: English
Classifier: Operating System :: OS Independent
Classifier: Programming Language :: Python
Classifier: Programming Language :: Python :: 3
Classifier: Programming Language :: Python :: 3.3
Classifier: Programming Language :: Python :: 3.4
Classifier: Programming Language :: Python :: 3.5
Requires-Dist: enum34
Requires-Dist: networkx
Requires-Dist: nose
Requires-Dist: numpy
Requires-Dist: pyenchant
Requires-Dist: testpackage (==2.26)
Requires-Dist: wheel
